<?xml version="1.0" encoding="UTF-8"?>
<objects serializationModel="Studio.02.03.00">
	<object class="EncodingSetting" id="{15c3f442-da18-4de3-a4d2-3ae00a5c6889}">
		<property name="encodingFormat">
			<value>3</value>
		</property>
		<property name="quality">
			<value>37</value>
		</property>
		<relationship name="platform">
			<destination>{9480d24a-761b-4d91-8d97-e39e80c0f0d9}</destination>
		</relationship>
		<relationship name="encodable">
			<destination>{c75a4936-2294-4bfb-a2ea-9f5c79716a26}</destination>
		</relationship>
	</object>
</objects>
